{
  "site": {
    "title": "Hämäränkävijät",
    "tagline": "Suomalainen mytologinen roolipeli",
    "microline": "Tarinoita, oppimista ja yhdessä pelaamista"
  },
  "navigation": {
    "main": "Main",
    "story": "Story",
    "blog": "Blog",
    "educators": "Educators",
    "downloads": "Downloads"
  },
  "pages": {
    "home": {
      "heroTitle": "Hämäränkävijät avaa oven suomalaiseen mytologiaan.",
      "heroBody": "Hämäränkävijät on roolipeli, jossa tarinat syntyvät yhdessä. Täältä löydät pelin tarinamaailman, opettajille suunnatun käytön ja ladattavat materiaalit.",
      "heroPrimary": "Lue tarinasta",
      "heroSecondary": "Opettajille",
      "audienceTitle": "Kenelle sivusto on tehty?",
      "audienceItems": [
        {
          "title": "Pelaajille",
          "body": "Nopea aloitus pelin maailmaan, tunnelmaan ja tarinalliseen pelaamiseen."
        },
        {
          "title": "Opettajille",
          "body": "Valmiit näkökulmat roolipelin käyttöön opetuksessa, ryhmätöissä ja ilmaisussa."
        },
        {
          "title": "Kerhoille ja kirjastoille",
          "body": "Toimivat mallit yhteisölliseen pelaamiseen matalalla aloituskynnyksellä."
        },
        {
          "title": "Sisällön seuraajille",
          "body": "Blogi kokoaa kehityksen, testikokemukset ja tulevat päivitykset."
        }
      ],
      "newsletterTitle": "Pysy mukana",
      "newsletterBody": "Liity uutiskirjeeseen ja saat kehitysmerkintöjä, testipelihakuja ja julkaisukuulumisia.",
      "newsletterButton": "Liity uutiskirjeeseen"
    },
    "story": {
      "heroTitle": "Mikä on Hämäränkävijöiden tarina?",
      "heroBody": "Hämäränkävijät yhdistää suomalaisen mytologian, yhteisen tarinankerronnan ja helposti lähestyttävän roolipelaamisen.",
      "principlesTitle": "Tarinan kulmakivet",
      "audienceItems": [
        {
          "title": "Suomalainen mytologia",
          "body": "Tarinat nojaavat tuttuun kansanperinteeseen, mutta jättävät tilaa omalle tulkinnalle."
        },
        {
          "title": "Yhteinen kerronta",
          "body": "Pelaajat rakentavat maailmaa yhdessä, eikä yksikään peli etene samalla tavalla."
        },
        {
          "title": "Selkeä pelattavuus",
          "body": "Säännöt tukevat tarinaa, jotta aloitus on nopea sekä uusille että kokeneille pelaajille."
        }
      ],
      "journalTitle": "Mistä aloittaa?",
      "journalBody": "Aloita tarinan perusteista ja jatka blogiin, jossa kerromme miten maailma kehittyy pelitestien myötä."
    },
    "educators": {
      "heroTitle": "Roolipeli opetuksessa",
      "heroBody": "Hämäränkävijät sopii opetukseen, nuorisotyöhön ja kerhotoimintaan. Sisällöt tukevat ilmaisua, yhteistyötä ja kulttuurista ymmärrystä.",
      "pillarsTitle": "Käytännön käyttötavat",
      "audienceItems": [
        {
          "title": "Äidinkieli ja ilmaisu",
          "body": "Tarinatehtävät vahvistavat lukutaitoa, keskustelua ja luovaa kirjoittamista."
        },
        {
          "title": "Ryhmätaidot",
          "body": "Pelaaminen harjoittaa kuuntelua, vuorottelua ja yhteistä ongelmanratkaisua."
        },
        {
          "title": "Kulttuurisisällöt",
          "body": "Suomalainen mytologia tarjoaa paikallista kontekstia historian ja kulttuurin käsittelyyn."
        }
      ],
      "contactTitle": "Materiaalit käyttöön",
      "contactBody": "Lataa valmiit materiaalit Downloads-sivulta ja ota ne käyttöön sellaisenaan tai muokattuina."
    },
    "downloads": {
      "heroTitle": "Lataukset",
      "heroBody": "Tältä sivulta löydät peliä tukevat ladattavat materiaalit. Päivitämme pakettia kehityksen edetessä.",
      "resourcesTitle": "Saatavilla nyt",
      "audienceItems": [
        {
          "title": "Pika-aloitus",
          "body": "Tiivis aloituspaketti ensimmäistä pelisessiota varten."
        },
        {
          "title": "Opettajan runko",
          "body": "Rakennemalli tunti- tai kerhokäyttöön tavoitteineen."
        },
        {
          "title": "Tulostettavat hahmolomakkeet",
          "body": "Helposti monistettavat lomakkeet nopeaan käyttöönottoon."
        }
      ],
      "newsletterTitle": "Tarvitsetko uuden tiedoston?",
      "newsletterBody": "Lisäämme uusia ladattavia materiaaleja blogipäivitysten yhteydessä."
    },
    "blog": {
      "heroTitle": "Blogi",
      "heroBody": "Päivityksiä pelitestauksesta, maailmarakennuksesta ja julkaisusuunnitelmasta.",
      "blogLead": "Uusimmat merkinnät"
    }
  }
}
